yamlfield/__init__.py
yamlfield/apps.py
yamlfield/fields.py
yamlfield/models.py
yamlfield/serializers.py
yamlfield/tests.py
django_yamlfield-1.2.2.dist-info/LICENSE
django_yamlfield-1.2.2.dist-info/METADATA
django_yamlfield-1.2.2.dist-info/WHEEL
django_yamlfield-1.2.2.dist-info/top_level.txt
django_yamlfield-1.2.2.dist-info/RECORD
